[
    {
        "user": [
            {
                "id": 1,
                "username": "craig",
                "password": "abcde",
                "created_At": "2017-10-01",
                "pictures": [
                    {
                        "id": "Object.id"
                    },
                    {
                        "id": "Object.id"
                    }
                ]
            },
            {
                "id": 2,
                "username": "ben",
                "password": "fghij",
                "created_At": "2017-11-01",
                "pictures": [
                    {
                        "id": 1,
                        "link": "./assets/image1.png"
                    },
                    {
                        "id": 2,
                        "link": "./assets/image2.png"
                    }
                ]
            }
        ],

        "picture": [
            {
                
            },
            {

            }
        ],

        "verdict": [
            {
                "id": 1,
                "verdict": true,
                "description": "Really like this picture",
                "userID": "Object.id",
                "pictureID": "Object.id"
            },
            {
                
            }
        ]
    }
]